standdown/__init__.py
standdown/__main__.py
standdown/cli.py
standdown/config.py
standdown/database.py
standdown/server.py
standdown-0.1.0.dist-info/licenses/LICENSE
standdown-0.1.0.dist-info/METADATA
standdown-0.1.0.dist-info/WHEEL
standdown-0.1.0.dist-info/entry_points.txt
standdown-0.1.0.dist-info/top_level.txt
standdown-0.1.0.dist-info/RECORD
