Metadata-Version: 2.4
Name: standdown
Version: 0.1.0
Summary: Minimal CLI and server for asynchronous standups
Author-email: Jovan Lukovic <jovanlukovic001@gmail.com>
License: AGPL-3.0-or-later
Requires-Python: >=3.7
License-File: LICENSE
Requires-Dist: fastapi
Requires-Dist: uvicorn
Requires-Dist: SQLAlchemy
Requires-Dist: colorama
Dynamic: license-file
